src/Client.py
src/__init__.py
src/cli.py
src/server_connection.py
src/server_constants.py
src/server_game.py
src/server_player.py
src/server_to_play.py
BACKSTABBING-0.0.8.dist-info/METADATA
BACKSTABBING-0.0.8.dist-info/WHEEL
BACKSTABBING-0.0.8.dist-info/entry_points.txt
BACKSTABBING-0.0.8.dist-info/top_level.txt
BACKSTABBING-0.0.8.dist-info/RECORD
